jrep/__init__.py
jrep/jrep.py
jrep/modded_glob.py
jrep/sre_compile.py
jrep/sre_constants.py
jrep/sre_parse.py
JREP-0.1.dist-info/LICENSE
JREP-0.1.dist-info/METADATA
JREP-0.1.dist-info/WHEEL
JREP-0.1.dist-info/entry_points.txt
JREP-0.1.dist-info/top_level.txt
JREP-0.1.dist-info/RECORD
