Metadata-Version: 2.1
Name: JREP
Version: 0.1
Summary: A CLI tool based on GREP designed for the modern world
Home-page: https://github.com/Scripter17/JREP
Author: James C. Wise
Author-email: jameschristopherwise@gmail.com
Project-URL: Bug Tracker, https://github.com/Scripter17/JREP/issues
Classifier: Programming Language :: Python :: 3
Classifier: Operating System :: OS Independent
Requires-Python: >=3.6
License-File: LICENSE
